pykiso/__init__.py
pykiso/__main__.py
pykiso/auxiliary.py
pykiso/cli.py
pykiso/config_parser.py
pykiso/connector.py
pykiso/endpoint.py
pykiso/exceptions.py
pykiso/expose/__init__.py
pykiso/expose/rest_server.py
pykiso/global_config.py
pykiso/interfaces/__init__.py
pykiso/interfaces/dt_auxiliary.py
pykiso/lib/__init__.py
pykiso/lib/auxiliaries/__init__.py
pykiso/lib/auxiliaries/acroname_auxiliary.py
pykiso/lib/auxiliaries/can_auxiliary/__init__.py
pykiso/lib/auxiliaries/can_auxiliary/can_auxiliary.py
pykiso/lib/auxiliaries/can_auxiliary/can_message.py
pykiso/lib/auxiliaries/can_auxiliary/can_parser.py
pykiso/lib/auxiliaries/communication_auxiliary.py
pykiso/lib/auxiliaries/dut_auxiliary.py
pykiso/lib/auxiliaries/instrument_control_auxiliary/__init__.py
pykiso/lib/auxiliaries/instrument_control_auxiliary/instrument_control_auxiliary.py
pykiso/lib/auxiliaries/instrument_control_auxiliary/instrument_control_cli.py
pykiso/lib/auxiliaries/instrument_control_auxiliary/lib_instruments.py
pykiso/lib/auxiliaries/instrument_control_auxiliary/lib_scpi_commands.py
pykiso/lib/auxiliaries/proxy_auxiliary.py
pykiso/lib/auxiliaries/record_auxiliary.py
pykiso/lib/auxiliaries/simulated_auxiliary/__init__.py
pykiso/lib/auxiliaries/simulated_auxiliary/response_templates.py
pykiso/lib/auxiliaries/simulated_auxiliary/scenario.py
pykiso/lib/auxiliaries/simulated_auxiliary/simulated_auxiliary.py
pykiso/lib/auxiliaries/simulated_auxiliary/simulation.py
pykiso/lib/auxiliaries/udsaux/__init__.py
pykiso/lib/auxiliaries/udsaux/common/__init__.py
pykiso/lib/auxiliaries/udsaux/common/odx_parser.py
pykiso/lib/auxiliaries/udsaux/common/uds_base_auxiliary.py
pykiso/lib/auxiliaries/udsaux/common/uds_callback.py
pykiso/lib/auxiliaries/udsaux/common/uds_exceptions.py
pykiso/lib/auxiliaries/udsaux/common/uds_request.py
pykiso/lib/auxiliaries/udsaux/common/uds_response.py
pykiso/lib/auxiliaries/udsaux/common/uds_utils.py
pykiso/lib/auxiliaries/udsaux/uds_auxiliary.py
pykiso-1.6.4.dist-info/METADATA
pykiso-1.6.4.dist-info/WHEEL
pykiso-1.6.4.dist-info/entry_points.txt
pykiso-1.6.4.dist-info/licenses/LICENSE
pykiso-1.6.4.dist-info/licenses/NOTICE.md
pykiso-1.6.4.dist-info/RECORD
