Metadata-Version: 2.4
Name: pykiso
Version: 1.6.4
Summary: Embedded integration testing framework.
License: Eclipse Public License - v 2.0
License-File: LICENSE
License-File: NOTICE.md
Keywords: testing,integration testing,framework,testing framework
Author: Sebastian Fischer
Author-email: sebastian.fischer@de.bosch.com
Requires-Python: >=3.10,<4.0
Classifier: Development Status :: 5 - Production/Stable
Classifier: Intended Audience :: Developers
Classifier: License :: OSI Approved :: Eclipse Public License 2.0 (EPL-2.0)
Classifier: License :: Other/Proprietary License
Classifier: Operating System :: MacOS
Classifier: Operating System :: Microsoft :: Windows
Classifier: Operating System :: POSIX
Classifier: Operating System :: Unix
Classifier: Programming Language :: Python
Classifier: Programming Language :: Python :: 3
Classifier: Programming Language :: Python :: 3.10
Classifier: Programming Language :: Python :: 3.11
Classifier: Programming Language :: Python :: 3.12
Classifier: Programming Language :: Python :: 3.13
Classifier: Programming Language :: Python :: 3.14
Classifier: Programming Language :: Python :: 3.9
Classifier: Programming Language :: Python :: Implementation :: CPython
Classifier: Topic :: Utilities
Provides-Extra: all
Provides-Extra: can
Provides-Extra: debugger
Provides-Extra: grpc
Provides-Extra: instrument
Provides-Extra: plugins
Provides-Extra: pykitest
Provides-Extra: serial
Provides-Extra: testrail
Requires-Dist: Jinja2 (>=3.0.0,<4.0.0)
Requires-Dist: MarkupSafe (>=2.0.1,<2.1.0)
Requires-Dist: PyVISA (>=1.12.0,<2.0.0) ; extra == "plugins" or extra == "instrument" or extra == "all"
Requires-Dist: PyVISA-py (>=0.5.3,<0.6.0) ; extra == "plugins" or extra == "instrument" or extra == "all"
Requires-Dist: PyYAML (>=6.0,<7.0)
Requires-Dist: black ; extra == "pykitest" or extra == "all"
Requires-Dist: brainstem
Requires-Dist: cantools (>=39.4.2,<40.0.0) ; python_version >= "3.8" and python_version < "4.0"
Requires-Dist: click (>=7.0.0,<9.0.0)
Requires-Dist: defusedxml (>=0.7.1,<0.8.0)
Requires-Dist: fastapi (>=0.115.3,<0.116.0)
Requires-Dist: grpcio (>=1.0.0,<2.0.0) ; extra == "grpc" or extra == "all"
Requires-Dist: hidapi (>=0.12,<0.15)
Requires-Dist: importlib-metadata (>=4.12,<7.0) ; python_version < "3.8"
Requires-Dist: isort (>=5.11.4) ; extra == "pykitest" or extra == "all"
Requires-Dist: junitparser (>=3.2.0,<4.0.0)
Requires-Dist: packaging
Requires-Dist: protobuf (>=4.24.2,<5.0.0) ; extra == "grpc" or extra == "all"
Requires-Dist: pykiso-python-uds (>=3.2.0,<3.3.0) ; extra == "plugins" or extra == "can" or extra == "all"
Requires-Dist: pylink-square (>=1.2.0,<1.3.0) ; extra == "plugins" or extra == "debugger" or extra == "all"
Requires-Dist: pyreadline3 (>=3.4.1,<4.0.0) ; python_version >= "3.5" and python_version < "4.0"
Requires-Dist: pyserial (>=3.0,<4.0) ; extra == "plugins" or extra == "serial" or extra == "all"
Requires-Dist: python-can[pcan,vector] (>=4.4.2,<4.5.0) ; extra == "plugins" or extra == "can" or extra == "all"
Requires-Dist: requests (>=2.28.2,<3.0.0) ; extra == "testrail" or extra == "all"
Requires-Dist: rich (>=13.2.0,<14.0.0) ; extra == "testrail" or extra == "all"
Requires-Dist: robotframework (==3.2.2)
Requires-Dist: tabulate (>=0.8.9,<0.10.0)
Requires-Dist: unittest-xml-reporting (>=3.2.0,<4.0.0)
Requires-Dist: uvicorn (>=0.32.0,<0.33.0)
Requires-Dist: viztracer (>=1.0.1,<2.0.0)
Requires-Dist: xmltodict (>=0.14.2,<0.15.0)
Project-URL: Documentation, https://kiso-testing.readthedocs.io/en/latest/
Project-URL: Homepage, https://pypi.org/project/pykiso/
Project-URL: Repository, https://github.com/eclipse/kiso-testing
